DESCRIPTION.rst
LICENSE
MANIFEST.in
README.md
setup.py
docs/README.md
docs/cnvs.md
docs/germline_snvs.md
docs/metadata.md
docs/somatic_snvs.md
docs/structural_variants.md
mtbparser/mtbparser_exception.py
mtbparser/snv_item.py
mtbparser/snv_parser.py
mtbparser/snv_utils.py
mtbparser.egg-info/PKG-INFO
mtbparser.egg-info/SOURCES.txt
mtbparser.egg-info/dependency_links.txt
mtbparser.egg-info/top_level.txt