Metadata-Version: 1.1
Name: mtbparser
Version: 0.2.4
Summary: A module that parses different diagnostic variant data.
Home-page: https://github.com/qbicsoftware/qbic.mtbparser
Author: Sven Fillinger
Author-email: sven.fillinger@qbic.uni-tuebingen.de
License: MIT
Platform: UNKNOWN
Classifier: Programming Language :: Python
Classifier: Programming Language :: Python :: 3.4
Classifier: Programming Language :: Python :: 3.5
Classifier: Intended Audience :: Developers
Classifier: Topic :: Software Development :: Libraries :: Python Modules
Classifier: Topic :: Scientific/Engineering :: Bio-Informatics
Classifier: License :: OSI Approved :: MIT License
